sylk_parser/__init__.py
sylk_parser/sylk.py
sylk_parser/sylk_parser.py
sylk_parser-0.5.dist-info/LICENSE.txt
sylk_parser-0.5.dist-info/METADATA
sylk_parser-0.5.dist-info/WHEEL
sylk_parser-0.5.dist-info/top_level.txt
sylk_parser-0.5.dist-info/RECORD
