Metadata-Version: 2.1
Name: sylk-parser
Version: 0.5
Summary: Basic SLK (sylk) to CSV parser
Home-page: https://github.com/majerteam/sylk_parser
Author: Majerti
Author-email: equipe@majerti.fr
License: GPLv3
Keywords: parser csv slk sylk
Platform: UNKNOWN
Classifier: License :: OSI Approved :: GNU General Public License v3 (GPLv3)
Classifier: Programming Language :: Python
Classifier: Programming Language :: Python :: 3
Classifier: Topic :: Software Development :: Libraries
Classifier: Intended Audience :: Developers
